[
  {
    "nit": "48628727",
    "url": "https://sistema.rgae.gob.gt/consulta-proveedores/proveedor/48628727?source=guatecompras",
    "status": "ENCONTRADO",
    "data": {
      "NIT": "48628727",
      "Nombre o razón social": "ANGEL MAURICIO GARCÍA PAREDES",
      "Representantes": [],
      "Comercios": [],
      "Especialidades": [],
      "Solicitudes": []
    }
  },
  {
    "nit": "110058003",
    "url": "https://sistema.rgae.gob.gt/consulta-proveedores/proveedor/110058003?source=guatecompras",
    "status": "ENCONTRADO",
    "data": {
      "NIT": "110058003",
      "Nombre o razón social": "DISTEXSA, SOCIEDAD ANÓNIMA",
      "Representantes": [],
      "Comercios": [],
      "Especialidades": [],
      "Solicitudes": []
    }
  },
  {
    "nit": "29356326",
    "url": "https://sistema.rgae.gob.gt/consulta-proveedores/proveedor/29356326?source=guatecompras",
    "status": "ENCONTRADO",
    "data": {
      "NIT": "29356326",
      "Nombre o razón social": "CELSO JESÚS PÉREZ ORTÍZ",
      "Representantes": [],
      "Comercios": [],
      "Especialidades": [],
      "Solicitudes": []
    }
  },
  {
    "nit": "120521792",
    "url": "https://sistema.rgae.gob.gt/consulta-proveedores/proveedor/120521792?source=guatecompras",
    "status": "ENCONTRADO",
    "data": {
      "NIT": "120521792",
      "Nombre o razón social": "CORPORACIÓN FERROAGRICOLA L&L, SOCIEDAD ANÓNIMA",
      "Representantes": [],
      "Comercios": [],
      "Especialidades": [],
      "Solicitudes": []
    }
  },
  {
    "nit": "117193771",
    "url": "https://sistema.rgae.gob.gt/consulta-proveedores/proveedor/117193771?source=guatecompras",
    "status": "ENCONTRADO",
    "data": {
      "NIT": "117193771",
      "Nombre o razón social": "JOSÉ ESTUARDO RODAS",
      "Representantes": [],
      "Comercios": [],
      "Especialidades": [],
      "Solicitudes": []
    }
  },
  {
    "nit": "32824467",
    "url": "https://sistema.rgae.gob.gt/consulta-proveedores/proveedor/32824467?source=guatecompras",
    "status": "ENCONTRADO",
    "data": {
      "NIT": "32824467",
      "Nombre o razón social": "MELVYN DE JESÚS PÉREZ ARRIAGA",
      "Representantes": [],
      "Comercios": [],
      "Especialidades": [],
      "Solicitudes": []
    }
  },
  {
    "nit": "96428457",
    "url": "https://sistema.rgae.gob.gt/consulta-proveedores/proveedor/96428457?source=guatecompras",
    "status": "ENCONTRADO",
    "data": {
      "NIT": "96428457",
      "Nombre o razón social": "EDWIN GIOVANNI VÁSQUEZ VELÁSQUEZ",
      "Estado Actual": "No Actualizado",
      "Fecha de Inscripción": "23/12/2025",
      "Representantes": [],
      "Comercios": [
        {
          "nombre": "PANADERÍA Y PASTELERÍA DON WINO",
          "direccion": "SECTOR 1 LOTE 111 APTO. A ZONA 0 COLONIA SAN JULIÁN NUEVA CHINAUTLA 13 AVENIDA A CHINAUTLA,GUATEMALA"
        }
      ],
      "Especialidades": [],
      "Solicitudes": [
        {
          "numero": "INSC2025183407",
          "tipo": "Inscripción de Comerciante Individual",
          "estado": "Finalizada",
          "fechaAprobacion": "23/12/2025",
          "constancia": "",
          "resolucion": ""
        }
      ]
    }
  },
  {
    "nit": "89938577",
    "url": "https://sistema.rgae.gob.gt/consulta-proveedores/proveedor/89938577?source=guatecompras",
    "status": "ENCONTRADO",
    "data": {
      "NIT": "89938577",
      "Nombre o razón social": "WILLIAM DAVID QUINÁ SIMÓN",
      "Representantes": [],
      "Comercios": [],
      "Especialidades": [],
      "Solicitudes": []
    }
  },
  {
    "nit": "11810815",
    "url": "https://sistema.rgae.gob.gt/consulta-proveedores/proveedor/11810815?source=guatecompras",
    "status": "ENCONTRADO",
    "data": {
      "NIT": "11810815",
      "Nombre o razón social": "ERITA MARELÍ POLANCO MEDRANO",
      "Representantes": [],
      "Comercios": [],
      "Especialidades": [],
      "Solicitudes": []
    }
  },
  {
    "nit": "120713128",
    "url": "https://sistema.rgae.gob.gt/consulta-proveedores/proveedor/120713128?source=guatecompras",
    "status": "ENCONTRADO",
    "data": {
      "NIT": "120713128",
      "Nombre o razón social": "ANIMAL WORLD, SOCIEDAD ANÓNIMA",
      "Representantes": [],
      "Comercios": [],
      "Especialidades": [],
      "Solicitudes": []
    }
  },
  {
    "nit": "1204076",
    "url": "https://sistema.rgae.gob.gt/consulta-proveedores/proveedor/1204076?source=guatecompras",
    "status": "ENCONTRADO",
    "data": {
      "NIT": "1204076",
      "Nombre o razón social": "DROGUERIA REFASA , SOCIEDAD ANONIMA",
      "Estado Actual": "Precalificado",
      "Fecha de Inscripción": "03/07/2019",
      "Fecha Última Precalificación": "12/08/2024",
      "Tipo de Precalificación": "Precalificacion de Bienes, Servicios y Suministros",
      "Vigencia de Última Precalificación": "12/08/2026",
      "Representantes": [
        {
          "nit": "5663989",
          "pais": "Guatemala",
          "pasaporte": "",
          "nombre": "PABLO DAVID GALVEZ MONZON"
        },
        {
          "nit": "234753",
          "pais": "Guatemala",
          "pasaporte": "",
          "nombre": "GILDA ESTELA MONZON HURTADO DE GALVEZ"
        },
        {
          "nit": "14842424",
          "pais": "Guatemala",
          "pasaporte": "",
          "nombre": "DANIEL ALFONSO MAZARIEGOS MAURICIO"
        }
      ],
      "Comercios": [
        {
          "nombre": "REFASA",
          "direccion": "2 CALLE 3-75 ZONA 1 GUATEMALA,GUATEMALA"
        }
      ],
      "Especialidades": [],
      "Solicitudes": [
        {
          "numero": "APTR2026131020",
          "tipo": "Ampliación de Proveedores Transparentes",
          "estado": "Finalizada",
          "fechaAprobacion": "14/07/2026",
          "constancia": "",
          "resolucion": ""
        },
        {
          "numero": "ACSO202620624",
          "tipo": "Actualización de inscripción de sociedad",
          "estado": "Finalizada",
          "fechaAprobacion": "16/01/2026",
          "constancia": "",
          "resolucion": ""
        },
        {
          "numero": "APTR2025122361",
          "tipo": "Ampliación de Proveedores Transparentes",
          "estado": "Finalizada",
          "fechaAprobacion": "26/05/2025",
          "constancia": "",
          "resolucion": ""
        },
        {
          "numero": "ACSO202518506",
          "tipo": "Actualización de inscripción de sociedad",
          "estado": "Finalizada",
          "fechaAprobacion": "15/01/2025",
          "constancia": "",
          "resolucion": ""
        },
        {
          "numero": "CPS2024146110",
          "tipo": "Constancia adicional de precalificación de bienes, suministros y servicios",
          "estado": "Finalizada",
          "fechaAprobacion": "11/12/2024",
          "constancia": "",
          "resolucion": ""
        },
        {
          "numero": "CPS2024143897",
          "tipo": "Constancia adicional de precalificación de bienes, suministros y servicios",
          "estado": "Finalizada",
          "fechaAprobacion": "02/12/2024",
          "constancia": "",
          "resolucion": ""
        },
        {
          "numero": "PREP2024111500",
          "tipo": "Precalificación proveedores de bienes, suministros y servicios",
          "estado": "Finalizada",
          "fechaAprobacion": "12/08/2024",
          "constancia": "",
          "resolucion": ""
        },
        {
          "numero": "ACSO202421777",
          "tipo": "Actualización de inscripción de sociedad",
          "estado": "Finalizada",
          "fechaAprobacion": "18/01/2024",
          "constancia": "",
          "resolucion": ""
        },
        {
          "numero": "CPS2023138698",
          "tipo": "Constancia adicional de precalificación de bienes, suministros y servicios",
          "estado": "Finalizada",
          "fechaAprobacion": "18/12/2023",
          "constancia": "",
          "resolucion": ""
        },
        {
          "numero": "CPS2023123963",
          "tipo": "Constancia adicional de precalificación de bienes, suministros y servicios",
          "estado": "Finalizada",
          "fechaAprobacion": "27/09/2023",
          "constancia": "",
          "resolucion": ""
        },
        {
          "numero": "CPS2023119101",
          "tipo": "Constancia adicional de precalificación de bienes, suministros y servicios",
          "estado": "Finalizada",
          "fechaAprobacion": "21/08/2023",
          "constancia": "",
          "resolucion": ""
        },
        {
          "numero": "CPS2023111442",
          "tipo": "Constancia adicional de precalificación de bienes, suministros y servicios",
          "estado": "Finalizada",
          "fechaAprobacion": "10/07/2023",
          "constancia": "",
          "resolucion": ""
        },
        {
          "numero": "CPS202395141",
          "tipo": "Constancia adicional de precalificación de bienes, suministros y servicios",
          "estado": "Finalizada",
          "fechaAprobacion": "19/04/2023",
          "constancia": "",
          "resolucion": ""
        },
        {
          "numero": "ACSO20232200",
          "tipo": "Actualización de inscripción de sociedad",
          "estado": "Finalizada",
          "fechaAprobacion": "20/01/2023",
          "constancia": "",
          "resolucion": ""
        },
        {
          "numero": "PREP202295601",
          "tipo": "Precalificación proveedores de bienes, suministros y servicios",
          "estado": "Finalizada",
          "fechaAprobacion": "02/08/2022",
          "constancia": "",
          "resolucion": ""
        },
        {
          "numero": "CPS202283488",
          "tipo": "Constancia adicional de precalificación de bienes, suministros y servicios",
          "estado": "Finalizada",
          "fechaAprobacion": "01/03/2022",
          "constancia": "",
          "resolucion": ""
        },
        {
          "numero": "ACSO202251724",
          "tipo": "Actualización de inscripción de sociedad",
          "estado": "Finalizada",
          "fechaAprobacion": "17/02/2022",
          "constancia": "",
          "resolucion": ""
        },
        {
          "numero": "CPS2021143555",
          "tipo": "Constancia adicional de precalificación de bienes, suministros y servicios",
          "estado": "Finalizada",
          "fechaAprobacion": "18/11/2021",
          "constancia": "",
          "resolucion": ""
        },
        {
          "numero": "CPS2021126029",
          "tipo": "Constancia adicional de precalificación de bienes, suministros y servicios",
          "estado": "Finalizada",
          "fechaAprobacion": "06/08/2021",
          "constancia": "",
          "resolucion": ""
        },
        {
          "numero": "CPS2021113740",
          "tipo": "Constancia adicional de precalificación de bienes, suministros y servicios",
          "estado": "Finalizada",
          "fechaAprobacion": "02/06/2021",
          "constancia": "",
          "resolucion": ""
        },
        {
          "numero": "CPS2021108076",
          "tipo": "Constancia adicional de precalificación de bienes, suministros y servicios",
          "estado": "Finalizada",
          "fechaAprobacion": "06/05/2021",
          "constancia": "",
          "resolucion": ""
        },
        {
          "numero": "ACSO202135837",
          "tipo": "Actualización de inscripción de sociedad",
          "estado": "Finalizada",
          "fechaAprobacion": "24/01/2021",
          "constancia": "",
          "resolucion": ""
        },
        {
          "numero": "CPS2020127801",
          "tipo": "Constancia adicional de precalificación de bienes, suministros y servicios",
          "estado": "Finalizada",
          "fechaAprobacion": "10/12/2020",
          "constancia": "",
          "resolucion": ""
        },
        {
          "numero": "PREP202098899",
          "tipo": "Precalificación proveedores de bienes, suministros y servicios",
          "estado": "Finalizada",
          "fechaAprobacion": "03/08/2020",
          "constancia": "",
          "resolucion": ""
        },
        {
          "numero": "CPS202089888",
          "tipo": "Constancia adicional de precalificación de bienes, suministros y servicios",
          "estado": "Finalizada",
          "fechaAprobacion": "11/06/2020",
          "constancia": "",
          "resolucion": ""
        },
        {
          "numero": "CIS202089733",
          "tipo": "Constancia adicional de inscripción de sociedad",
          "estado": "Finalizada",
          "fechaAprobacion": "10/06/2020",
          "constancia": "",
          "resolucion": ""
        },
        {
          "numero": "ACSO202048587",
          "tipo": "Actualización de inscripción de sociedad",
          "estado": "Finalizada",
          "fechaAprobacion": "04/02/2020",
          "constancia": "",
          "resolucion": ""
        },
        {
          "numero": "PREP201964509",
          "tipo": "Precalificación proveedores de bienes, suministros y servicios",
          "estado": "Finalizada",
          "fechaAprobacion": "19/07/2019",
          "constancia": "",
          "resolucion": ""
        },
        {
          "numero": "INSS201961343",
          "tipo": "Inscripción de Sociedad",
          "estado": "Finalizada",
          "fechaAprobacion": "03/07/2019",
          "constancia": "",
          "resolucion": ""
        },
        {
          "numero": "CTP20183073",
          "tipo": "Inscripcion y precalificacion transitoria Bienes y Servicios",
          "estado": "Finalizada",
          "fechaAprobacion": "29/11/2018",
          "constancia": "",
          "resolucion": ""
        }
      ]
    }
  },
  {
    "nit": "120909758",
    "url": "https://sistema.rgae.gob.gt/consulta-proveedores/proveedor/120909758?source=guatecompras",
    "status": "ENCONTRADO",
    "data": {
      "NIT": "120909758",
      "Nombre o razón social": "FASHION ORIENTAL, SOCIEDAD ANÓNIMA",
      "Representantes": [],
      "Comercios": [],
      "Especialidades": [],
      "Solicitudes": []
    }
  },
  {
    "nit": "120831147",
    "url": "https://sistema.rgae.gob.gt/consulta-proveedores/proveedor/120831147?source=guatecompras",
    "status": "ENCONTRADO",
    "data": {
      "NIT": "120831147",
      "Nombre o razón social": "INVERSIONES JC, SOCIEDAD ANÓNIMA",
      "Representantes": [],
      "Comercios": [],
      "Especialidades": [],
      "Solicitudes": []
    }
  },
  {
    "nit": "120456613",
    "url": "https://sistema.rgae.gob.gt/consulta-proveedores/proveedor/120456613?source=guatecompras",
    "status": "ENCONTRADO",
    "data": {
      "NIT": "120456613",
      "Nombre o razón social": "INVERSIONES GRUPO FERSA, SOCIEDAD ANÓNIMA",
      "Representantes": [],
      "Comercios": [],
      "Especialidades": [],
      "Solicitudes": []
    }
  },
  {
    "nit": "18165257",
    "url": "https://sistema.rgae.gob.gt/consulta-proveedores/proveedor/18165257?source=guatecompras",
    "status": "ENCONTRADO",
    "data": {
      "NIT": "18165257",
      "Nombre o razón social": "UNIVERSIDAD PANAMERICANA",
      "Estado Actual": "No Actualizado",
      "Fecha de Inscripción": "26/06/2019",
      "Fecha Última Precalificación": "26/06/2019",
      "Tipo de Precalificación": "Precalificacion de Firmas Consultoras",
      "Vigencia de Última Precalificación": "31/12/2019",
      "Representantes": [],
      "Comercios": [],
      "Especialidades": [],
      "Solicitudes": [
        {
          "numero": "IPRF201944893",
          "tipo": "Inscripción y precalificación Asociación, Fundación, ONG´s y otras entidades jurídicas firmas consultora",
          "estado": "Finalizada",
          "fechaAprobacion": "26/06/2019",
          "constancia": "",
          "resolucion": ""
        },
        {
          "numero": "CTP201950962",
          "tipo": "Inscripcion y precalificacion transitoria Bienes y Servicios",
          "estado": "Finalizada",
          "fechaAprobacion": "06/05/2019",
          "constancia": "",
          "resolucion": ""
        }
      ]
    }
  },
  {
    "nit": "120817721",
    "url": "https://sistema.rgae.gob.gt/consulta-proveedores/proveedor/120817721?source=guatecompras",
    "status": "ENCONTRADO",
    "data": {
      "NIT": "120817721",
      "Nombre o razón social": "CORPORACIÓN OSWARD, SOCIEDAD ANÓNIMA",
      "Representantes": [],
      "Comercios": [],
      "Especialidades": [],
      "Solicitudes": []
    }
  },
  {
    "nit": "109310047",
    "url": "https://sistema.rgae.gob.gt/consulta-proveedores/proveedor/109310047?source=guatecompras",
    "status": "ENCONTRADO",
    "data": {
      "NIT": "109310047",
      "Nombre o razón social": "ANTHONY JEREMY'S DE JESÚS ROMERO REYNA",
      "Representantes": [],
      "Comercios": [],
      "Especialidades": [],
      "Solicitudes": []
    }
  }
]